pyarcanist/__init__.py
pyarcanist/__main__.py
pyarcanist/cache.py
pyarcanist/cli.py
pyarcanist/diff.py
pyarcanist/harbormaster.py
pyarcanist/tools.py
pyarcanist/whoami.py
pyarcanist-0.0.1.dist-info/LICENSE
pyarcanist-0.0.1.dist-info/METADATA
pyarcanist-0.0.1.dist-info/WHEEL
pyarcanist-0.0.1.dist-info/entry_points.txt
pyarcanist-0.0.1.dist-info/top_level.txt
pyarcanist-0.0.1.dist-info/RECORD
