Metadata-Version: 2.1
Name: pyarcanist
Version: 0.0.1
Summary: Pure python cli for Phabricator
Home-page: https://forge.softwareheritage.org/source/pyarcanist/
Author: Software Heritage developers
Author-email: swh-devel@inria.fr
License: UNKNOWN
Platform: UNKNOWN
Classifier: Programming Language :: Python :: 3
Classifier: Intended Audience :: Developers
Classifier: License :: OSI Approved :: GNU General Public License v3 (GPLv3)
Classifier: Operating System :: OS Independent
Classifier: Development Status :: 3 - Alpha
Requires-Dist: beaker
Requires-Dist: click
Requires-Dist: gitpython
Requires-Dist: humanize
Requires-Dist: phabricator
